[ {"date": "2025-03-13", "artist": "A-Ha", "title": "Take On Me", "id": "GK0hisiU6-c"},{"date": "2025-03-13", "artist": "Alice In Chains", "title": "Down in a Hole", "id": "SBqnQwPMx1Y"},{"date": "2025-03-13", "artist": "Aqua", "title": "Barbie Girl", "id": "W28FCLk0dJo"},{"date": "2025-03-13", "artist": "Aqua", "title": "Barbie Girl (Duet)", "id": "ozn8o_U2sE4"},{"date": "2025-03-13", "artist": "Armed, The", "title": "Where Man Knows Want", "id": "OHN1hzc9MDg"},{"date": "2025-03-13", "artist": "Edith Piaf", "title": "La Vie en Rose", "id": "4c4myH5kbo0"},{"date": "2025-03-13", "artist": "Jack Stauber", "title": "Peppermint (Duet, abbr.)", "id": "67onZapdCaw"},{"date": "2025-03-13", "artist": "Nine Inch Nails", "title": "Right Where It Belongs", "id": "0UFE7B2Fkcw"},{"date": "2025-03-13", "artist": "Right Said Fred", "title": "I'm Too Sexy", "id": "qZxUDyMTrzY"},{"date": "2025-03-13", "artist": "Alvvays", "title": "Archie, Marry Me", "id": "ZgTv7XGEMig"},{"date": "2025-03-13", "artist": "Armed, The", "title": "AN ITERATION", "id": "n3fWSAZzgaY"},{"date": "2025-03-13", "artist": "Billy Ray Cyrus", "title": "Achy Breaky Heart", "id": "QIRrJlwFMHg"},{"date": "2025-03-13", "artist": "CAKE", "title": "Satan Is My Motor", "id": "2d9-GV35Wjo"},{"date": "2025-03-13", "artist": "Doja Cat", "title": "Say So", "id": "Bl2AbaX85mw"},{"date": "2025-03-13", "artist": "Doja Cat", "title": "Tia Tamera ft. Rico Nasty", "id": "hLGnZilWKnQ"},{"date": "2025-03-13", "artist": "Faye Webster", "title": "Kingston", "id": "VXQCdjGiw1U"},{"date": "2025-03-13", "artist": "Frank Ocean", "title": "Pink + White", "id": "UCAH9fX6Iwg"},{"date": "2025-03-13", "artist": "Julia Jacklin", "title": "Someday", "id": "JpAs7f3pglo"},{"date": "2025-03-13", "artist": "Lady Gaga", "title": "Paparazzi", "id": "nsWuCsBHhMY"},{"date": "2025-03-13", "artist": "Marcy Playground", "title": "Sex and Candy", "id": "EBImUtdKhnw"},{"date": "2025-03-13", "artist": "Mars Volta, The", "title": "L'Via L'Viaquez", "id": "hD4XZuIObQc"},{"date": "2025-03-13", "artist": "Mars Volta, The", "title": "Son et Lumi\ufffdre & Inertiatic ESP", "id": "HlbKh7rVkzk"},{"date": "2025-03-13", "artist": "Mars Volta, The", "title": "The Widow", "id": "VULAvpu7FOQ"},{"date": "2025-03-13", "artist": "Metric", "title": "Black Sheep", "id": "VplDWXSHiEs"},{"date": "2025-03-13", "artist": "Neon Genesis Evangelion", "title": "Zankoku na Tenshi no Teze (Main Theme)", "id": "kfREg0i6eOM"},{"date": "2025-03-13", "artist": "Phoebe Bridgers", "title": "Kyoto", "id": "Nu2TZ3jGK_U"},{"date": "2025-03-13", "artist": "Postal Service, The", "title": "Nothing Better (Duet)", "id": "aET4quuzPPM"},{"date": "2025-03-13", "artist": "Postal Service, The", "title": "Such Great Heights", "id": "kQmHUruKaUw"},{"date": "2025-03-13", "artist": "SAMIA", "title": "Someone Tell the Boys", "id": "lZs2T-Z58gA"},{"date": "2025-03-13", "artist": "Saweetie", "title": "Best Friend ft. Doja Cat", "id": "LjGf1vVIPis"},{"date": "2025-03-13", "artist": "Shins, The", "title": "Gone for Good", "id": "HA69WyJhKp4"},{"date": "2025-03-13", "artist": "Trapt", "title": "HeadStrong", "id": "oTSru9yYVH8"},{"date": "2025-03-13", "artist": "Unicorns, The", "title": "I Was Born a Unicorn", "id": "orzqL3Y7Kck"},{"date": "2025-02-27", "artist": "Korn", "title": "Another Brick in the Wall", "id": "3RFmrY_Seks"},{"date": "2025-02-27", "artist": "Sonic Adventure 2", "title": "Escape from the City", "id": "5bjULQizgfw"},{"date": "2025-02-27", "artist": "Sonic Adventure", "title": "Believe in Myself (Tails' Theme)", "id": "JDlQARZS31Y"},{"date": "2025-02-27", "artist": "Sonic Adventure", "title": "It Doesn't Matter (Sonic's Theme)", "id": "G2nte_pmPQE"},{"date": "2025-02-27", "artist": "Sonic Adventure", "title": "Lazy Days (Duet) (Big's Theme)", "id": "eYHWFFGHilI"},{"date": "2025-02-27", "artist": "Sonic Adventure", "title": "My Sweet Passion (Amy's Theme)", "id": "V27E3gYrnXQ"},{"date": "2025-02-27", "artist": "Sonic Adventure", "title": "Open Your Heart (Main Theme)", "id": "IYW_SCSKJXw"},{"date": "2025-02-27", "artist": "Sonic Adventure", "title": "Unknown from M.E. (Knuckles' Theme)", "id": "16P-TFAEutU"},{"date": "2025-02-27", "artist": "Sonic Adventure 2", "title": "Believe in Myself (Tails' Theme)", "id": "rM5gnVG8DbQ"},{"date": "2025-02-27", "artist": "Sonic Adventure 2", "title": "E.G.G.M.A.N. (Eggman's Theme)", "id": "7AJX9N0ZzaY"},{"date": "2025-02-27", "artist": "Sonic Adventure 2", "title": "Fly in the Freedom (Rouge's Theme)", "id": "XmUB3KG_RIQ"},{"date": "2025-02-27", "artist": "Sonic Adventure 2", "title": "It Doesn't Matter (Sonic's Theme)", "id": "hUcir7t_MIs"},{"date": "2025-02-27", "artist": "Sonic Adventure 2", "title": "Live & Learn (Main Theme)", "id": "ozaYTjYygzc"},{"date": "2025-02-27", "artist": "Sonic Adventure 2", "title": "Supporting Me (Biolizard's Theme)", "id": "wObdxUwInIg"},{"date": "2025-02-27", "artist": "Sonic Adventure 2", "title": "Throw It All Away (Shadow's Theme)", "id": "zfOuMz15wxg"},{"date": "2025-02-27", "artist": "Sonic Adventure 2", "title": "Unknown from M.E. (Knuckles' Theme)", "id": "vD3mXoZLH0s"},{"date": "2025-02-27", "artist": "Big Data", "title": "Dangerous ft. Joywave", "id": "Az5ClEj9eiY"},{"date": "2025-02-27", "artist": "Limp Bizkit", "title": "Behind Blue Eyes", "id": "B0lyg3DPeqI"},{"date": "2025-02-27", "artist": "Puddle of Mudd", "title": "Blurry", "id": "nzUt8H3lcqg"},{"date": "2025-02-27", "artist": "Radiohead", "title": "How to Disappear Completely", "id": "gRVO2CeOTOE"},{"date": "2025-02-27", "artist": "Radiohead", "title": "In Limbo", "id": "y0MeKjbx3ns"},{"date": "2025-02-27", "artist": "Butthole Surfers", "title": "Pepper", "id": "0vtXdXRtxAM"},{"date": "2025-02-27", "artist": "FIFTY FIFTY", "title": "Cupid (Twin version, Sped up)", "id": "69hoU1OdJjQ"},{"date": "2025-02-27", "artist": "Puddle of Mudd", "title": "She Hates Me", "id": "ZNfNc3W8m6A"},{"date": "2025-02-27", "artist": "Staind", "title": "It's Been Awhile", "id": "fMMCdBJS_Bs"},{"date": "2025-02-27", "artist": "Tears for Fears", "title": "Change", "id": "E9LvUNKl1KU"},{"date": "2025-02-27", "artist": "Trapt", "title": "Headstrong", "id": "oTSru9yYVH8"},{"date": "2025-02-27", "artist": "Ween", "title": "Transdermal Celebration", "id": "waAomUNzHgs"},{"date": "2025-02-27", "artist": "Ween", "title": "Your Party", "id": "22Okf1eWm4I"},{"date": "2024-11-21", "artist": "A Day to Remember", "title": "Since U Been Gone", "id": "v8OByNS0H-A"},{"date": "2024-11-21", "artist": "Alice in Chains", "title": "Down In A Hole", "id": "SBqnQwPMx1Y"},{"date": "2024-11-21", "artist": "Alice in Chains", "title": "I Stay Away (no backing vocals)", "id": "Xi4HCBaVr6s"},{"date": "2024-11-21", "artist": "Alice in Chains", "title": "I Stay Away (w backing vocals)", "id": "vOGzcX_FBJw"},{"date": "2024-11-21", "artist": "Alice in Chains", "title": "Man in the Box", "id": "S4Y9Z0-F8q4"},{"date": "2024-11-21", "artist": "Alice in Chains", "title": "Rooster", "id": "7-kiOBGtQ8A"},{"date": "2024-11-21", "artist": "Alice in Chains", "title": "Would", "id": "O__gNwK70y8"},{"date": "2024-11-21", "artist": "Audioslave", "title": "I Am the Highway", "id": "RBx5LTWTpeY"},{"date": "2024-11-21", "artist": "Audioslave", "title": "Show Me How to Live", "id": "SNvTfkFkmg8"},{"date": "2024-11-21", "artist": "Bad Omens", "title": "Like a Villain", "id": "58raSIFlrII"},{"date": "2024-11-21", "artist": "Bad Omens", "title": "The Death of Peace of Mind", "id": "EYugkXp8TD4"},{"date": "2024-11-21", "artist": "Blue Oyster Cult", "title": "Godzilla", "id": "kDO648hBwZE"},{"date": "2024-11-21", "artist": "Breaking Benjamin", "title": "Diary of Jane", "id": "S19uam2_48g"},{"date": "2024-11-21", "artist": "Chappell Roan", "title": "Good Luck, Babe!", "id": "DjkCfplHxww"},{"date": "2024-11-21", "artist": "Chappell Roan", "title": "Pink Pony Club", "id": "d4L7iymCVHk"},{"date": "2024-11-21", "artist": "Chappell Roan", "title": "Red Wine Supernova", "id": "h9iOmGY0zRM"},{"date": "2024-11-21", "artist": "Chevelle", "title": "The Red", "id": "ASdMdGH2rVI"},{"date": "2024-11-21", "artist": "Darkness, The", "title": "I Believe in a Thing Called Love", "id": "g_mMdLr2RSE"},{"date": "2024-11-21", "artist": "Evanescence", "title": "Bring Me to Life", "id": "frpfRwGv6KU"},{"date": "2024-11-21", "artist": "Evanescence", "title": "Everybody's Fool", "id": "kzAre14LqGI"},{"date": "2024-11-21", "artist": "Evanescence", "title": "Going Under", "id": "hmgPwlcQHHg"},{"date": "2024-11-21", "artist": "Evanescence", "title": "Lithium", "id": "dFq7PxiKCj8"},{"date": "2024-11-21", "artist": "Frozen", "title": "Let It Go", "id": "ifCAfAzOBJM"},{"date": "2024-11-21", "artist": "Hercules", "title": "I Won't Say (I'm In Love)", "id": "QJmL664nLhA"},{"date": "2024-11-21", "artist": "Hozier", "title": "Movement", "id": "eLmQdlz4jwI"},{"date": "2024-11-21", "artist": "Hozier", "title": "Someone New", "id": "9lXGUYe4osQ"},{"date": "2024-11-21", "artist": "Incubus", "title": "Anna Molly", "id": "fB1sEcCynkE"},{"date": "2024-11-21", "artist": "Incubus", "title": "Dig", "id": "jyN_1P4VG6U"},{"date": "2024-11-21", "artist": "Incubus", "title": "Love Hurts", "id": "ZEts2sOpzro"},{"date": "2024-11-21", "artist": "Incubus", "title": "Pardon Me", "id": "aB-CPShxMBk"},{"date": "2024-11-21", "artist": "Incubus", "title": "Stellar", "id": "5FIZMAAD9VQ"},{"date": "2024-11-21", "artist": "Jax", "title": "Victoria's Secret", "id": "_RD5Yf3Vu6Q"},{"date": "2024-11-21", "artist": "Killers, The", "title": "Glamorous Indie Rock & Roll", "id": "1b6ibQJaZwY"},{"date": "2024-11-21", "artist": "Linkin Park", "title": "In the End", "id": "uIcmAyAJ5hE"},{"date": "2024-11-21", "artist": "Linkin Park", "title": "Numb", "id": "umUTLZ06Gsw"},{"date": "2024-11-21", "artist": "Nine Inch Nails", "title": "Only", "id": "qYmNBRV1-PE"},{"date": "2024-11-21", "artist": "Nine Inch Nails", "title": "Something I Can Never Have", "id": "7NgfqVMp2yQ"},{"date": "2024-11-21", "artist": "Paramore", "title": "All I Wanted", "id": "sOtdXKWtHyo"},{"date": "2024-11-21", "artist": "Puscifer", "title": "Potions", "id": "08LyYJGByAA"},{"date": "2024-11-21", "artist": "Puscifer", "title": "Rev 22 20", "id": "i6UwExrlI2A"},{"date": "2024-11-21", "artist": "Queen", "title": "I'm Going Slightly Mad", "id": "-ZQcFdhSMtw"},{"date": "2024-11-21", "artist": "Rihanna", "title": "Umbrella (No Rap)", "id": "ra3UzdpfoBg"},{"date": "2024-11-21", "artist": "Rihanna", "title": "Umbrella ft. Jay-Z", "id": "xgLuhXNrUz8"},{"date": "2024-11-21", "artist": "Say Anything", "title": "Alive with the Glory of Love", "id": "fDCtFP5sKNg"},{"date": "2024-11-21", "artist": "Sixpence None the Richer", "title": "There She Goes", "id": "iWBfUT_UK-I"},{"date": "2024-11-21", "artist": "Slipknot", "title": "Before I Forget", "id": "MmsRaJNzNKE"},{"date": "2024-11-21", "artist": "Slipknot", "title": "Duality", "id": "OfWFfthYuW0"},{"date": "2024-11-21", "artist": "Slipknot", "title": "Snuff", "id": "t5dek0BpmXo"},{"date": "2024-11-21", "artist": "Slipknot", "title": "Vermillion, Pt. 2", "id": "4uDNHsdLgpI"},{"date": "2024-11-21", "artist": "Slipknot", "title": "Wait and Bleed", "id": "NTC3cMGpJ-I"},{"date": "2024-11-21", "artist": "Smashing Pumpkins, The", "title": "Bullet with Butterfly Wings", "id": "NdqZQERua_I"},{"date": "2024-11-21", "artist": "Smashing Pumpkins, The", "title": "Today", "id": "uhQ-g3yH52M"},{"date": "2024-11-21", "artist": "Smashing Pumpkins, The", "title": "Tonight, Tonight", "id": "RYmTacXZ6EM"},{"date": "2024-11-21", "artist": "Smashing Pumpkins, The", "title": "Zero", "id": "p2O74jis-Ys"},{"date": "2024-11-21", "artist": "Steven Universe", "title": "Do It for Her (Duet)", "id": "xfTd-7CuWKc"},{"date": "2024-11-21", "artist": "Steven Universe", "title": "Giant Woman", "id": "LPnje5jLyX8"},{"date": "2024-11-21", "artist": "Steven Universe", "title": "Something Entirely New (Duet)", "id": "SwqEnLTpiMM"},{"date": "2024-11-21", "artist": "Strokes, The", "title": "Last Nite", "id": "eYjsYelPAco"},{"date": "2024-11-21", "artist": "System of a Down", "title": "Toxicity", "id": "TXenLQdECkM"},{"date": "2024-11-21", "artist": "System of a Down", "title": "Violent Pornography", "id": "_GAHYn-cjJk"},{"date": "2024-11-21", "artist": "Tool", "title": "Sober", "id": "n3riqiLQb9U"},{"date": "2024-11-21", "artist": "Tool", "title": "Stinkfist", "id": "Qz5ckGJJFhQ"},{"date": "2024-11-21", "artist": "Wicked", "title": "Defying Gravity", "id": "_ce778S_3iI"},{"date": "2024-11-21", "artist": "Alkaline Trio", "title": "This Could Be Love", "id": "AKZ-LRXOUVs"},{"date": "2024-11-21", "artist": "Blackbear", "title": "Hot Girl Bummer", "id": "NfGSgwfgUik"},{"date": "2024-11-21", "artist": "Datarock", "title": "Amarillion", "id": "h3vVM9LJp0E"},{"date": "2024-11-21", "artist": "Gims", "title": "Bella", "id": "Udvca55Raf0"},{"date": "2024-11-21", "artist": "Gims", "title": "Cam\ufffdl\ufffdon", "id": "_NJZRDmXCAk"},{"date": "2024-11-21", "artist": "Gims", "title": "Est-ce Que Tu M'aimes", "id": "K1iANopVspc"},{"date": "2024-11-21", "artist": "MIKA", "title": "Elle Me Dit", "id": "gL7hhM0Qx6Q"},{"date": "2024-11-21", "artist": "Rihanna", "title": "Umbrella (no rap)", "id": "ra3UzdpfoBg"},{"date": "2024-11-21", "artist": "Stromae", "title": "Alors On Danse", "id": "p1fzVQ6yzU0"},{"date": "2024-11-21", "artist": "Stromae", "title": "Carmen", "id": "6p7cIkheLag"},{"date": "2024-11-21", "artist": "Stromae", "title": "Formidable", "id": "nf2AEzMwYFM"},{"date": "2024-11-21", "artist": "Stromae", "title": "Papaoutai", "id": "CUO2UTYy2Oo"},{"date": "2024-10-17", "artist": "Adam and the Ants", "title": "Stand and Deliver", "id": "FdkOPfTmj3c"},{"date": "2024-10-17", "artist": "Amigo the Devil", "title": "Murder at the Bingo Hall", "id": "EDHoSj-YDps"},{"date": "2024-10-17", "artist": "Black Sabbath", "title": "Heaven and Hell", "id": "8AJjXNYrFHA"},{"date": "2024-10-17", "artist": "British Sea Power", "title": "The Smallest Church in Saint-Sa\ufffdns", "id": "E3UUFd_gTv0"},{"date": "2024-10-17", "artist": "Bruce Springsteen", "title": "The Ghost of Tom Joad", "id": "yx9AtcQWXVg"},{"date": "2024-10-17", "artist": "Cage the Elephant", "title": "Ain't No Rest for the Wicked", "id": "0su6Ovfbetk"},{"date": "2024-10-17", "artist": "Change", "title": "Tears for Fears", "id": "E9LvUNKl1KU"},{"date": "2024-10-17", "artist": "Childish Gambino", "title": "Redbone (Clean)", "id": "yM0VA66F7CQ"},{"date": "2024-10-17", "artist": "Crane Wives, The", "title": "Curses", "id": "VH79fXG5BL4"},{"date": "2024-10-17", "artist": "Cure, The", "title": "The Lovecats", "id": "CcB7-bjWXEU"},{"date": "2024-10-17", "artist": "Cutting Crew", "title": "(I Just) Died in Your Arms", "id": "uLbdaJaokuc"},{"date": "2024-10-17", "artist": "David Bowie", "title": "Lady Stardust", "id": "9QLQ3-iL8j0"},{"date": "2024-10-17", "artist": "David Bowie", "title": "Rock 'n' Roll With Me", "id": "AAbtMuIb7XA"},{"date": "2024-10-17", "artist": "Decemberists, The", "title": "Here I Dreamt I Was an Architect", "id": "mxJppHMe7yQ"},{"date": "2024-10-17", "artist": "Decemberists, The", "title": "O Valencia!", "id": "6jZDyBh0eUQ"},{"date": "2024-10-17", "artist": "Decemberists, The", "title": "The Chimbley Sweep", "id": "-4E1oIUIEuI"},{"date": "2024-10-17", "artist": "Decemberists, The", "title": "The Legionnaire's Lament", "id": "aDsA2EXVV4k"},{"date": "2024-10-17", "artist": "Decemberists, The", "title": "Yankee Bayonet (I Will Be Home Then)", "id": "IFK57PekHqk"},{"date": "2024-10-17", "artist": "Eurythmics", "title": "Sweet Dreams (Are Made of This) (Remix)", "id": "-f0Zqxmfm1o"},{"date": "2024-10-17", "artist": "Everything Everything", "title": "Cold Reactor", "id": "w4gyA9MlWao"},{"date": "2024-10-17", "artist": "Gnarls Barkley", "title": "Crazy", "id": "ekPbSYMtU6o"},{"date": "2024-10-17", "artist": "Gnarls Barkley", "title": "Smiley Faces", "id": "zCmThy5wWeg"},{"date": "2024-10-17", "artist": "Janelle Mon\ufffde", "title": "Electric Lady", "id": "DBDEjIxCrnQ"},{"date": "2024-10-17", "artist": "Lemon Demon", "title": "Touch-Tone Telephone", "id": "XCzVjPsaJpk"},{"date": "2024-10-17", "artist": "Lord Huron", "title": "Vide Noir", "id": "TxWr4rkQIUc"},{"date": "2024-10-17", "artist": "Lord Huron", "title": "When the Night Is Over", "id": "GMtguv0QI_k"},{"date": "2024-10-17", "artist": "Miike Snow", "title": "Genghis Khan", "id": "Zu5g1VNjkQ8"},{"date": "2024-10-17", "artist": "Nemo", "title": "The Code", "id": "GwBkAipkRUY"},{"date": "2024-10-17", "artist": "New Order", "title": "Hey Now What You Doing", "id": "ukebJ3o9144"},{"date": "2024-10-17", "artist": "New Order", "title": "Temptation", "id": "nMZi83WoD2c"},{"date": "2024-10-17", "artist": "Police, The", "title": "King of Pain", "id": "ySEkLJU4G04"},{"date": "2024-10-17", "artist": "Police, The", "title": "Synchronicity II", "id": "uK2zkOfcQyk"},{"date": "2024-10-17", "artist": "Police, The", "title": "Wrapped Around Your Finger", "id": "wNC4a-I-ic8"},{"date": "2024-10-17", "artist": "Revivalists, The", "title": "Wish I Knew You", "id": "jkE0LehXml0"},{"date": "2024-10-17", "artist": "Sting", "title": "The Soul Cages", "id": "fRzGGhGocNI"},{"date": "2024-10-17", "artist": "Talking Heads", "title": "This Must Be The Place (Naive Melody)", "id": "ZMP2kb7SgXE"},{"date": "2024-10-17", "artist": "Trans-Siberian Orchestra", "title": "What Is Eternal", "id": "KIf0bN7PmXo"},{"date": "2024-10-17", "artist": "Type O Negative", "title": "Love You to Death", "id": "qhtfW7S76RQ"},{"date": "2024-10-17", "artist": "ZZ Ward", "title": "Til The Casket Drops", "id": "7Pdv5hWhf0U"},{"date": "2024-10-17", "artist": "Crazy World of Arthur Brown, The", "title": "Fire", "id": "573mpEzsmhM"},{"date": "2024-10-17", "artist": "Cardigans, The & Tom Jones", "title": "Burning Down the House (Duet)", "id": "EByXYdGhAHo"},{"date": "2024-10-17", "artist": "Gotye ft. Kimbra", "title": "Somebody That I Used To Know", "id": "7zYoDiWvwN4"},{"date": "2024-10-17", "artist": "Gotye ft. Kimbra", "title": "Somebody That I Used To Know (Duet)", "id": "Zxll-M2ULMI"},{"date": "2024-10-17", "artist": "LCD Soundsystem", "title": "New York, I Love You But You're Bringing...", "id": "3ytAUwJlMsk"},{"date": "2024-10-17", "artist": "April Smith and the Great Picture Show", "title": "Dixie Boy", "id": "gm0Ta7t2p6c"},{"date": "2024-10-17", "artist": "Kid Rock", "title": "Picture ft. Sheryl Crow (Duet)", "id": "tuP6LczqLR4"},{"date": "2024-10-17", "artist": "Kim Petras", "title": "There Will Be Blood", "id": "jkffV6VNfbA"},{"date": "2024-10-17", "artist": "Olivia Rodrigo", "title": "Get Him Back", "id": "SrzM3HOtKsY"},{"date": "2024-10-17", "artist": "Saint Motel", "title": "My Type", "id": "6X0XtuJ3D2E"},{"date": "2024-10-17", "artist": "Sky Ferreira", "title": "Heavy Metal Heart", "id": "3arqjGnagfM"},{"date": "2024-10-17", "artist": "Sweet", "title": "Ballroom Blitz", "id": "KQY8P3mb7ZI"},{"date": "2024-10-17", "artist": "Thermals, The", "title": "Let Your Earth Quake, Baby", "id": "nHabbKalm3E"},{"date": "2024-10-17", "artist": "Thermals, The", "title": "Returning to the Fold", "id": "CcNDAQ4vdII"},{"date": "2024-10-17", "artist": "Toh Kay", "title": "Shantantitty Town", "id": "3_e0v26-JI0"},{"date": "2024-10-17", "artist": "Ying Yang Twins", "title": "Wait (The Whisper Song)", "id": "KDoD_har7UU"},{"date": "2024-09-28", "artist": "Chumbawamba", "title": "Tubthumping", "id": "HtbMqSts8dI"},{"date": "2024-09-27", "artist": "All Time Low ", "title": "Dear Maria, Count Me In", "id": "hlteotxlnIc"},{"date": "2024-09-27", "artist": "Chappell Roan", "title": "Casual", "id": "-A58t72ENz4"},{"date": "2024-09-27", "artist": "Childish Gambino", "title": "Redbone", "id": "VtlB9rCmv1k"},{"date": "2024-09-27", "artist": "Cosmo Sheldrake", "title": "Does the Swallow Dream of Flying", "id": "SPIDJWFUny0"},{"date": "2024-09-27", "artist": "Coyote Kid", "title": "Destroyer of Worlds", "id": "yNkxVQbIzsQ"},{"date": "2024-09-27", "artist": "Earth, Wind & Fire", "title": "September", "id": "cKRmRYad318"},{"date": "2024-09-27", "artist": "Eric Hutchinson", "title": "OK, It's Alright With Me", "id": "e3JEKAA-SwI"},{"date": "2024-09-27", "artist": "Fish in a Birdcage", "title": "Rule #34", "id": "iMOlsvkvjN4"},{"date": "2024-09-27", "artist": "Friday Pilots Club", "title": "Would You Mind", "id": "SAI5f5Su7ig"},{"date": "2024-09-27", "artist": "Fugees", "title": "Killing Me Softly with His Song", "id": "DKTlrfsLuhA"},{"date": "2024-09-27", "artist": "I Don't Know How But They Found Me", "title": "Absinthe", "id": "672T0ZKlE6I"},{"date": "2024-09-27", "artist": "Jazmine Sullivan", "title": "Bust Your Windows", "id": "KK1rnzOk0Ts"},{"date": "2024-09-27", "artist": "Killers, The", "title": "Somebody Told Me", "id": "p11rc6Qhuho"},{"date": "2024-09-27", "artist": "Lana Del Rey", "title": "Million Dollar Man", "id": "vQ2R_8iRfzU"},{"date": "2024-09-27", "artist": "Les Gold", "title": "Silver Platters", "id": "Nd0sBLIVXi4"},{"date": "2024-09-27", "artist": "Longest Johns, The", "title": "Oak & Ash & Thorn", "id": "TEucI4vU3KQ"},{"date": "2024-09-27", "artist": "Madds Buckley", "title": "The Red Means I Love You", "id": "6WpSJEfWHmg"},{"date": "2024-09-27", "artist": "Mariah Carey", "title": "We Belong Together", "id": "xMt1vHky0m4"},{"date": "2024-09-27", "artist": "Mario", "title": "Let Me Love You", "id": "xEwPVphGS70"},{"date": "2024-09-27", "artist": "Miguel", "title": "Coffee", "id": "zH7EHKEnpzE"},{"date": "2024-09-27", "artist": "Miguel", "title": "Sure Thing", "id": "Iilqpt9eC4k"},{"date": "2024-09-27", "artist": "Miley Cyrus", "title": "Party in the USA", "id": "kfa-26JfdDA"},{"date": "2024-09-27", "artist": "My Chemical Romance", "title": "Vampires Will Never Hurt You", "id": "ChBzIOODxAE"},{"date": "2024-09-27", "artist": "Ne-Yo", "title": "So Sick (Duet)", "id": "M3Q9A7QWWFI"},{"date": "2024-09-27", "artist": "Panic! At The Disco", "title": "I Write Sins Not Tragedies", "id": "Eby9kjH3wXE"},{"date": "2024-09-27", "artist": "Pomplamoose", "title": "Bust Your Knee Caps", "id": "n0SFVEnPyFM"},{"date": "2024-09-27", "artist": "R. Kelly", "title": "Ignition (Remix)", "id": "0PnMNxfgoGA"},{"date": "2024-09-27", "artist": "Sammy Rae & the Friends", "title": "Closer To You", "id": "ao7r6wNvzHc"},{"date": "2024-09-27", "artist": "Sisqo", "title": "Thong Song", "id": "wqX5xwrxJ2U"},{"date": "2024-09-27", "artist": "Super Cassette", "title": "Be Gay, Do Drugs, Hail Satan", "id": "Q0Xi3PSCGhA"},{"date": "2024-09-27", "artist": "TLC", "title": "No Scrubs", "id": "CUFIRtDz-Oo"},{"date": "2024-09-27", "artist": "Trey Songz", "title": "Neighbors Know My Name", "id": "rMy152Lt6_Y"},{"date": "2024-09-27", "artist": "Usher", "title": "Burn", "id": "giE8oV3AI44"},{"date": "2024-09-27", "artist": "Usher", "title": "Confessions Part II", "id": "PCWe2TO0kfo"},{"date": "2024-09-27", "artist": "Valerie Broussard", "title": "A Little Wicked", "id": "qPmm9S66JsM"},{"date": "2024-09-26", "artist": "Adventure Time", "title": "Monster", "id": "OwME3OP8UPo"},{"date": "2024-09-26", "artist": "Alvin and the Chipmunks", "title": "Walk Like an Egyptian (16 speed)", "id": "9CAerD91Go8"},{"date": "2024-09-26", "artist": "Barry McGuire", "title": "Eve of Destruction", "id": "A_kDX6LeTEY"},{"date": "2024-09-26", "artist": "Beach Bunny", "title": "Dream Boy", "id": "okCNazRkwTw"},{"date": "2024-09-26", "artist": "Beach Bunny", "title": "Prom Queen", "id": "oo4WyB9JBGk"},{"date": "2024-09-26", "artist": "Beach Bunny", "title": "Sports", "id": "DBOEo9mudE4"},{"date": "2024-09-26", "artist": "Bo Burnham", "title": "Welcome to the Internet", "id": "FK0vZWztu80"},{"date": "2024-09-26", "artist": "Bo Burnham", "title": "White Woman's Instagram", "id": "9vhlO2DHRCs"},{"date": "2024-09-26", "artist": "Cardigans, The", "title": "I Need Some Fine Wine and You...", "id": "sFyviAlfKHM"},{"date": "2024-09-26", "artist": "Cardigans, The", "title": "Iron Man", "id": "wuKh6S1dnag"},{"date": "2024-09-26", "artist": "Cardigans, The", "title": "Sabbath Bloody Sabbath", "id": "18nz5d7HCgI"},{"date": "2024-09-26", "artist": "Charly Bliss", "title": "Capacity", "id": "6TAU7_P8iLE"},{"date": "2024-09-26", "artist": "Charly Bliss", "title": "Hard to Believe", "id": "-sDD0zOvYDw"},{"date": "2024-09-26", "artist": "Charly Bliss", "title": "Percolator", "id": "K6MDCakJjTc"},{"date": "2024-09-26", "artist": "Classics IV, The", "title": "Spooky", "id": "ILS6vA_HaK8"},{"date": "2024-09-26", "artist": "d4vd", "title": "My House Is Not a Home", "id": "sbwdgfWo7a0"},{"date": "2024-09-26", "artist": "d4vd", "title": "Romantic Homicide", "id": "6gJOFTj-z_I"},{"date": "2024-09-26", "artist": "Dazey and the Scouts", "title": "Wet", "id": "B2iJHV7c2Ok"},{"date": "2024-09-26", "artist": "Destroy Boys", "title": "Crybaby", "id": "jyIAStOu2TU"},{"date": "2024-09-26", "artist": "Devo", "title": "Gut Feeling, Slap Your Mammy", "id": "AcMa0xcv3Qg"},{"date": "2024-09-26", "artist": "Doors, The", "title": "The End", "id": "xltxNkvBDt8"},{"date": "2024-09-26", "artist": "Foo Fighters", "title": "Pretender, The", "id": "78G5rQjRJgM"},{"date": "2024-09-26", "artist": "Gerry Rafferty", "title": "Baker Street", "id": "tsMX_mc2YOM"},{"date": "2024-09-26", "artist": "Gil Scott-Heron", "title": "The Revolution Will Not Be Televised", "id": "dMoJZobS2kM"},{"date": "2024-09-26", "artist": "Gone Jackals, The", "title": "Legacy", "id": "Jz-KwErV6DU"},{"date": "2024-09-26", "artist": "Helluva Boss", "title": "House of Asmodeus (several singers)", "id": "Kb8nUTl49F4"},{"date": "2024-09-26", "artist": "JVKE", "title": "This Is What Falling in Love Feels Like", "id": "UGjAkeEM0oA"},{"date": "2024-09-26", "artist": "Kaden MacKay", "title": "Passing Through (Can't the Future...)", "id": "5yRGOHRejO8"},{"date": "2024-09-26", "artist": "Laufey", "title": "From the Start", "id": "3vCD1mQlDlg"},{"date": "2024-09-26", "artist": "Midnight Oil", "title": "Beds Are Burning", "id": "vJ1WaVVmfL8"},{"date": "2024-09-26", "artist": "Mountain Goats, The", "title": "Fall of the Star High School Running Back", "id": "zWZryvEFj6c"},{"date": "2024-09-26", "artist": "Neighbourhood, The", "title": "Sweater Weather", "id": "0k91tvnkmMc"},{"date": "2024-09-26", "artist": "Neil Diamond", "title": "I Am... I Said", "id": "NqKO9XckCGg"},{"date": "2024-09-26", "artist": "Olivia Rodrigo", "title": "Love Is Embarrassing", "id": "FGHVhjHAV0k"},{"date": "2024-09-26", "artist": "Remember Sports", "title": "Clean Jeans", "id": "WGZbGPOfYds"},{"date": "2024-09-26", "artist": "Remember Sports", "title": "I Liked You Best", "id": "87uPcAe-zx0"},{"date": "2024-09-26", "artist": "Remember Sports", "title": "Saturday", "id": "7SVP0RiIg50"},{"date": "2024-09-26", "artist": "Remember Sports", "title": "Tiny Planets", "id": "34TfM0R4lZ8"},{"date": "2024-09-26", "artist": "Rick Derringer", "title": "Real American", "id": "5IZZoOKAzI8"},{"date": "2024-09-26", "artist": "Saliva", "title": "Rest in Pieces", "id": "rrDNZA_ENkA"},{"date": "2024-09-26", "artist": "Sam Smith", "title": "Unholy ft. Kim Petras", "id": "CNQecEnK26s"},{"date": "2024-09-26", "artist": "Sia", "title": "Chandelier (piano version)", "id": "qUP5mDujZrE"},{"date": "2024-09-26", "artist": "Smiths, The", "title": "There Is a Light That Never Goes Out", "id": "jkULDIk23KU"},{"date": "2024-09-26", "artist": "Steven Universe", "title": "We Are the Crystal Gems", "id": "OoosAVDzT3U"},{"date": "2024-09-26", "artist": "Tears for Fears", "title": "Shout", "id": "-pgdNctLVVc"},{"date": "2024-09-26", "artist": "Tears for Fears", "title": "Sowing the Seeds of Love", "id": "rR3FNiCZrYg"},{"date": "2024-09-26", "artist": "Tom Petty and the Heartbreakers", "title": "Don't Come Around Here No More", "id": "W8UAKcD7x70"},{"date": "2024-09-26", "artist": "Twenty One Pilots", "title": "Heathens", "id": "hYMHaamhiKU"},{"date": "2024-09-26", "artist": "Twenty One Pilots", "title": "Nico and the Niners", "id": "Vd_WTH_ZpJg"},{"date": "2024-09-26", "artist": "Twenty One Pilots", "title": "Shy Away", "id": "Z8F84X71Dgo"},{"date": "2024-09-26", "artist": "Twenty One Pilots", "title": "Tear in My Heart", "id": "sYvfQMhnsnQ"},{"date": "2024-09-26", "artist": "Yellowcard", "title": "Ocean Avenue", "id": "q-9fMb7Mr1I"},{"date": "2024-08-16", "artist": "Adriano Celentano", "title": "Prisencolinensinainciusol", "id": "-Td-kOcglTE"},{"date": "2024-08-16", "artist": "Bob Seger", "title": "Night Moves", "id": "9LZTxUgU1WU"},{"date": "2024-08-16", "artist": "Italian Folk Music", "title": "Bella Ciao", "id": "zxaqDcGkT68"},{"date": "2024-08-16", "artist": "Proclaimers, The", "title": "I'm Gonna Be (500 Miles)", "id": "UPO2QQ70P3Y"},{"date": "2024-08-16", "artist": "Scatman John", "title": "Scatman (Ski-Ba-Bop-Ba-Dop-Bop)", "id": "Z1zhzAbeNgs"},{"date": "2024-08-16", "artist": "Tom Waits", "title": "Clap Hands", "id": "qtgjOf6qBgg"},{"date": "2024-08-16", "artist": "Vanilla Fudge", "title": "You Keep Me Hangin' On", "id": "WSpqACfTsvA"},{"date": "2024-08-16", "artist": "Wolfe Tones", "title": "Come Out Ye Black & Tans", "id": "DvjrBg4BtLs"},{"date": "2024-08-15", "artist": "ABBA", "title": "Waterloo", "id": "wphW2H4ucg4"},{"date": "2024-08-15", "artist": "Adriano Celentano", "title": "Prisencolinensinainciusol", "id": "-Td-kOcglTE"},{"date": "2024-08-15", "artist": "AFI", "title": "Girl's Not Grey", "id": "RClCFFtXPKM"},{"date": "2024-08-15", "artist": "AFI", "title": "Miss Murder", "id": "eniwR_fndkw"},{"date": "2024-08-15", "artist": "AJJ", "title": "Bad Bad Things", "id": "lAamDD8Vzvw"},{"date": "2024-08-15", "artist": "AJJ", "title": "Brave as a Noun & Survival Song", "id": "Z8HK6GQQXN0"},{"date": "2024-08-15", "artist": "AJJ", "title": "People II, The Reckoning", "id": "zHxHBDoqyaQ"},{"date": "2024-08-15", "artist": "AJJ", "title": "Rejoice", "id": "upGNnAkL2jQ"},{"date": "2024-08-15", "artist": "Alien Ant Farm", "title": "Smooth Criminal", "id": "oYWjvV1vDdA"},{"date": "2024-08-15", "artist": "Bombpops, The", "title": "CA in July", "id": "U67y6NRA1u8"},{"date": "2024-08-15", "artist": "Cake", "title": "War Pigs", "id": "1hvcyva1Bv8"},{"date": "2024-08-15", "artist": "Captain Lou Albano", "title": "The Super Mario Bros Super Show Theme", "id": "IQTwBagRrk4"},{"date": "2024-08-15", "artist": "Cardigans, The", "title": "Fine", "id": "yJ_J4i1EkFY"},{"date": "2024-08-15", "artist": "Cardigans, The", "title": "Happy Meal", "id": "r648RAYk-2Q"},{"date": "2024-08-15", "artist": "Cardigans, The", "title": "I Need Some Fine Wine and You, You Need to Be Nicer", "id": "sFyviAlfKHM"},{"date": "2024-08-15", "artist": "Cardigans, The", "title": "Lovefool", "id": "A7gF5FAs6zQ"},{"date": "2024-08-15", "artist": "Cardigans, The", "title": "My Favourite Game", "id": "XuifRLbSdso"},{"date": "2024-08-15", "artist": "Cardigans, The", "title": "Rise & Shine", "id": "tEnasjV_v3M"},{"date": "2024-08-15", "artist": "Cardigans, The", "title": "Sick & Tired", "id": "GfFuDriL-9Q"},{"date": "2024-08-15", "artist": "Chicks, The", "title": "Landslide", "id": "wE9pTIpP_QM"},{"date": "2024-08-15", "artist": "Creed", "title": "Higher", "id": "ud-5azVRG9E"},{"date": "2024-08-15", "artist": "Creed", "title": "My Own Prison", "id": "RbqQcmHHyx0"},{"date": "2024-08-15", "artist": "Creed", "title": "My Sacrifice", "id": "q8NW5NoSN8s"},{"date": "2024-08-15", "artist": "Creed", "title": "One Last Breath", "id": "5Bnth5PeS8Y"},{"date": "2024-08-15", "artist": "Depeche Mode", "title": "Blasphemous Rumours", "id": "MwDoo8_jPzA"},{"date": "2024-08-15", "artist": "Dolly Parton", "title": "9 to 5", "id": "OqQz92Od-HU"},{"date": "2024-08-15", "artist": "Eve 6", "title": "Inside Out", "id": "VSDNgt8YXKI"},{"date": "2024-08-15", "artist": "Good Charlotte", "title": "My Bloody Valentine (no backing vocals)", "id": "0fe2DivgkkE"},{"date": "2024-08-15", "artist": "Good Charlotte", "title": "My Bloody Valentine (w backing vocals)", "id": "gpa9zbaxxFg"},{"date": "2024-08-15", "artist": "Harvey Danger", "title": "Carlotta Valdez", "id": "A3VWwilH--A"},{"date": "2024-08-15", "artist": "Harvey Danger", "title": "Flagpole Sitta", "id": "8mYq6ilaY28"},{"date": "2024-08-15", "artist": "Kid Rock", "title": "Picture ft. Sheryl Crow", "id": "CPO-Y0nvkYI"},{"date": "2024-08-15", "artist": "Marty Robbins", "title": "El Paso", "id": "YkDzAbeq2mE"},{"date": "2024-08-15", "artist": "Marty Robbins", "title": "They're Hanging Me Tonight", "id": "ZzTy7dqEgNE"},{"date": "2024-08-15", "artist": "Metric", "title": "Help I'm Alive", "id": "wtwQYHNe1Hc"},{"date": "2024-08-15", "artist": "Modest Mouse", "title": "Dance Hall", "id": "ftMudLtrG_g"},{"date": "2024-08-15", "artist": "Mountain Goats, The", "title": "Best Ever Death Metal Band in Denton, The", "id": "PRhuKMEzc7E"},{"date": "2024-08-15", "artist": "Mountain Goats, The", "title": "Damn These Vampires", "id": "oF_5N2duO-M"},{"date": "2024-08-15", "artist": "Mountain Goats, The", "title": "Fall of the Star High School Running Back, The", "id": "zWZryvEFj6c"},{"date": "2024-08-15", "artist": "Mountain Goats, The", "title": "Foreign Object", "id": "trtK0XZxxwg"},{"date": "2024-08-15", "artist": "Mountain Goats, The", "title": "Mess Inside, The", "id": "nFkUvtvdLzo"},{"date": "2024-08-15", "artist": "Mountain Goats, The", "title": "No Children (no backing vocals)", "id": "4a03CjBAABg"},{"date": "2024-08-15", "artist": "Mountain Goats, The", "title": "No Children (w backing vocals)", "id": "_Z6MA5nlGXg"},{"date": "2024-08-15", "artist": "Mountain Goats, The", "title": "See America Right", "id": "npl_3mj2Pps"},{"date": "2024-08-15", "artist": "Mountain Goats, The", "title": "Up the Wolves", "id": "9MBO9GlhqaA"},{"date": "2024-08-15", "artist": "Mountain Goats, The", "title": "Werewolf Gimmick", "id": "Hm3n6yiaSy0"},{"date": "2024-08-15", "artist": "Muse", "title": "Hysteria", "id": "_JNGZPNmaVk"},{"date": "2024-08-15", "artist": "Muse", "title": "Madness", "id": "eXG0p_e8qzs"},{"date": "2024-08-15", "artist": "Muse", "title": "Starlight", "id": "NuJdcha4imw"},{"date": "2024-08-15", "artist": "Muse", "title": "Supermassive Black Hole", "id": "PeOgrmDdmOc"},{"date": "2024-08-15", "artist": "Muse", "title": "Undisclosed Desires", "id": "dmfeIDn_p48"},{"date": "2024-08-15", "artist": "Muse", "title": "Uprising", "id": "8jsDN5Pipj8"},{"date": "2024-08-15", "artist": "Muse", "title": "Will of the People", "id": "6M3da3GpxnM"},{"date": "2024-08-15", "artist": "Nickelback", "title": "How You Remind Me", "id": "7aMu6SNmBXg"},{"date": "2024-08-15", "artist": "Nickelback", "title": "Photograph", "id": "qTphCTAUhUg"},{"date": "2024-08-15", "artist": "Nickelback", "title": "Someday", "id": "ZquYhvD-vUg"},{"date": "2024-08-15", "artist": "Pat the Bunny", "title": "From Here to Utopia", "id": "SG57capWDNs"},{"date": "2024-08-15", "artist": "Pat the Bunny", "title": "Your Heart is a Muscle the Size of Your Fist", "id": "u5Q1D4Jy16U"},{"date": "2024-08-15", "artist": "Patsy Cline", "title": "Crazy", "id": "7Qj3rb4dJsM"},{"date": "2024-08-15", "artist": "Pixies", "title": "Hey", "id": "Lh_aytGu-60"},{"date": "2024-08-15", "artist": "Prodigy", "title": "Firestarter", "id": "CDV4vKJYJFk"},{"date": "2024-08-15", "artist": "Saliva", "title": "Rest in Pieces", "id": "rrDNZA_ENkA"},{"date": "2024-08-15", "artist": "Talking Heads", "title": "Once in a Lifetime", "id": "UKFD-b1dfJc"},{"date": "2024-08-15", "artist": "Tennessee Ernie Ford", "title": "Union Dixie", "id": "1io7mEns1kM"},{"date": "2024-08-15", "artist": "Thermals, The", "title": "A Pillar of Salt", "id": "4LxWQ7YgvNs"},{"date": "2024-08-15", "artist": "Thermals, The", "title": "No Culture Icons", "id": "A69hQ4yEEaM"},{"date": "2024-08-15", "artist": "Thermals, The", "title": "St. Rosa and the Swallows", "id": "P2UCHogiNrU"},{"date": "2024-08-15", "artist": "Tom Waits", "title": "16 Shells from a Thirty-Ought-Six", "id": "mhiEn5wdDyA"},{"date": "2024-08-15", "artist": "Tom Waits", "title": "Cemetery Polka", "id": "5sseUhObbk0"},{"date": "2024-08-15", "artist": "Tom Waits", "title": "Clap Hands", "id": "AvVvFbwgxRE"},{"date": "2024-08-15", "artist": "Tom Waits", "title": "I Hope That I Don't Fall in Love With You", "id": "aCL9NGxf-XY"},{"date": "2024-08-15", "artist": "Tom Waits", "title": "Jockey Full of Bourbon", "id": "GZGcc7k0PIw"},{"date": "2024-08-15", "artist": "Tom Waits", "title": "Piano Has Been Drinking, The", "id": "blaL3Jp3RxQ"},{"date": "2024-08-15", "artist": "Tom Waits", "title": "Rain Dogs", "id": "riZIvOxPNug"},{"date": "2024-08-15", "artist": "Twenty One Pilots", "title": "Heavydirtysoul", "id": "dsczy56MLHY"},{"date": "2024-08-15", "artist": "Twenty One Pilots", "title": "Ride", "id": "QH4ozIW5enc"},{"date": "2024-08-15", "artist": "Twenty One Pilots", "title": "Stressed Out", "id": "vfjbwAlr1tY"},{"date": "2024-08-15", "artist": "Weezer", "title": "No One Else", "id": "E93l-APkjQQ"},{"date": "2024-08-15", "artist": "Weezer", "title": "Susanne", "id": "Z1rGFIOYKwI"},{"date": "2024-08-15", "artist": "Weezer", "title": "Why Bother", "id": "ZaV_KQ8dKus"},{"date": "2024-08-15", "artist": "Weird Al Yankovic", "title": "Yoda", "id": "wZOolO6xjvQ"},{"date": "2024-08-15", "artist": "Wolfe Tones", "title": "Come Out Ye Black & Tans- DvjrBg4BtLs", "id": ""},{"date": "2024-08-15", "artist": "Yes", "title": "Owner of a Lonely Heart", "id": "UIaO5lW1rIw"} ]